happybase/TSaslClientTransport2.py
happybase/__init__.py
happybase/_version.py
happybase/batch.py
happybase/connection.py
happybase/pool.py
happybase/table.py
happybase/util.py
happybase/hbase/Hbase.py
happybase/hbase/__init__.py
happybase/hbase/constants.py
happybase/hbase/ttypes.py
sasl_happybase-1.0.dist-info/DESCRIPTION.rst
sasl_happybase-1.0.dist-info/METADATA
sasl_happybase-1.0.dist-info/RECORD
sasl_happybase-1.0.dist-info/WHEEL
sasl_happybase-1.0.dist-info/metadata.json
sasl_happybase-1.0.dist-info/top_level.txt
