Metadata-Version: 2.0
Name: sasl-happybase
Version: 1.0
Summary: A developer-friendly Python library to interact with Apache HBase with SASL support(Wait test)
Home-page: https://github.com/wbolster/happybase
Author: Wouter Bolsterlee
Author-email: uws@xs4all.nl
License: MIT
Platform: UNKNOWN
Classifier: Development Status :: 4 - Beta
Classifier: Intended Audience :: Developers
Classifier: License :: OSI Approved :: MIT License
Classifier: Programming Language :: Python :: 2
Classifier: Topic :: Database
Classifier: Topic :: Software Development :: Libraries :: Python Modules
Requires-Dist: thrift (>=0.9.2)
